Workbook
Name aporte: Projeto!$D$18
Name patrimonio: Projeto!$D$21
Name qtd_anos: Projeto!$D$19
Name rendimento_carteira: Projeto!$D$14
Name salario: Projeto!$D$13
Name sujestao: Projeto!$D$15
Name taxa_mensal: Projeto!$D$20

Sheet Projeto
B12: CONFIGURAÇÕES
B13: Salário | D13: 5000
B14: Rendimento Carteira | D14: 0.01
B15: Sugestão de Investimento (30%) | D15: =D13*30% -> 1500
B17: INVESTIMENTO MENSAL
B18: Quanto investir por mês? | D18: 1000
B19: Por quantos anos? | D19: 5
B20: Taxa de Rendimento mensal? | D20: 0.01
B21: Patrimonio acumulado? | D21: =FV(taxa_mensal,qtd_anos*12,aporte*-1) -> 81669.67
B22: Dividendos Mensais | D22: =patrimonio*taxa_mensal -> 816.6967
B24: CENÁRIOS | D24: DIVIDENDO
A25: 2 | B25: Quanto em 2 anos? | C25: =FV($D$20,$A25*12,$D$18*-1) -> 26973.465 | D25: =C25*rendimento_carteira -> 269.73465
A26: 5 | B26: Quanto em 5 anos? | C26: =FV($D$20,$A26*12,$D$18*-1) -> 81669.67 | D26: =C26*rendimento_carteira -> 816.6967
A27: 10 | B27: Quanto em 10 anos? | C27: =FV($D$20,$A27*12,$D$18*-1) -> 230038.69 | D27: =C27*rendimento_carteira -> 2300.3869
A28: 20 | B28: Quanto em 20 anos? | C28: =FV($D$20,$A28*12,$D$18*-1) -> 989255.37 | D28: =C28*rendimento_carteira -> 9892.5537
A29: 30 | B29: Quanto em 30 anos? | C29: =FV($D$20,$A29*12,$D$18*-1) -> 3494964.1 | D29: =C29*rendimento_carteira -> 34949.641
B32: PERFIL | C32: MODERADO
B33: Valor a ser investido por mês | C33: =aporte -> 1000
B35: TIPO DE FII | C35: PERCENTUAL SUGERIDO | D35: VALORES
B36: Papel | C36: =VLOOKUP($C$32&"-"&B36,Tab.Aux!A3:D20,4,) -> 0.32 | D36: =C36*$C$33 -> 320
B37: Tijolo | C37: =VLOOKUP($C$32&"-"&B37,Tab.Aux!A4:D21,4,) -> 0.35 | D37: =C37*$C$33 -> 350
B38: Híbridos | C38: =VLOOKUP($C$32&"-"&B38,Tab.Aux!A5:D22,4,) -> 0.08 | D38: =C38*$C$33 -> 80
B39: FOFs | C39: =VLOOKUP($C$32&"-"&B39,Tab.Aux!A6:D23,4,) -> 0.05 | D39: =C39*$C$33 -> 50
B40: Desenvolvimento | C40: =VLOOKUP($C$32&"-"&B40,Tab.Aux!A7:D24,4,) -> 0.1 | D40: =C40*$C$33 -> 100
B41: Hotelarias | C41: =VLOOKUP($C$32&"-"&B41,Tab.Aux!A8:D25,4,) -> 0.1 | D41: =C41*$C$33 -> 100
D42: =SUM(D36:D41) -> 1000

Sheet Tab.Aux
A2: CHAVE | B2: PERFIL | C2: TIPOS DE FII | D2: %
A3: =B3&"-"&C3 -> CONSERVADOR-Papel | B3: CONSERVADOR | C3: Papel | D3: 0.3
A4: =B4&"-"&C4 -> CONSERVADOR-Tijolo | B4: CONSERVADOR | C4: Tijolo | D4: 0.5
A5: =B5&"-"&C5 -> CONSERVADOR-Híbridos | B5: CONSERVADOR | C5: Híbridos | D5: 0.1
A6: =B6&"-"&C6 -> CONSERVADOR-FOFs | B6: CONSERVADOR | C6: FOFs | D6: 0.1
A7: =B7&"-"&C7 -> CONSERVADOR-Desenvolvimento | B7: CONSERVADOR | C7: Desenvolvimento | D7: 0
A8: =B8&"-"&C8 -> CONSERVADOR-Hotelarias | B8: CONSERVADOR | C8: Hotelarias | D8: 0
A9: =B9&"-"&C9 -> MODERADO-Papel | B9: MODERADO | C9: Papel | D9: 0.32
A10: =B10&"-"&C10 -> MODERADO-Tijolo | B10: MODERADO | C10: Tijolo | D10: 0.35
A11: =B11&"-"&C11 -> MODERADO-Híbridos | B11: MODERADO | C11: Híbridos | D11: 0.08
A12: =B12&"-"&C12 -> MODERADO-FOFs | B12: MODERADO | C12: FOFs | D12: 0.05
A13: =B13&"-"&C13 -> MODERADO-Desenvolvimento | B13: MODERADO | C13: Desenvolvimento | D13: 0.1
A14: =B14&"-"&C14 -> MODERADO-Hotelarias | B14: MODERADO | C14: Hotelarias | D14: 0.1
... A20: =B20&"-"&C20 -> AGRESSIVO-Hotelarias | B20: AGRESSIVO | C20: Hotelarias | D20: 0.1
